bbeval/__init__.py
bbeval/__main__.py
bbeval/cli.py
bbeval/grading.py
bbeval/models.py
bbeval/open_vscode_workspace.py
bbeval/signatures.py
bbeval/yaml_parser.py
bbeval-0.1.12.dist-info/METADATA
bbeval-0.1.12.dist-info/WHEEL
bbeval-0.1.12.dist-info/entry_points.txt
bbeval-0.1.12.dist-info/top_level.txt
bbeval-0.1.12.dist-info/RECORD
