Metadata-Version: 2.4
Name: bbeval
Version: 0.1.12
Summary: A lightweight, extensible evaluator for testing model-generated responses
License-Expression: MIT
Classifier: Development Status :: 3 - Alpha
Classifier: Intended Audience :: Developers
Classifier: Programming Language :: Python :: 3
Classifier: Programming Language :: Python :: 3.12
Classifier: Programming Language :: Python :: 3.13
Requires-Python: >=3.12
Requires-Dist: dspy-ai>=2.4.0
Requires-Dist: pyyaml>=6.0
Requires-Dist: pathlib2>=2.3.0
Requires-Dist: anthropic>=0.25.0
Requires-Dist: openai>=1.30.0
Requires-Dist: python-dotenv>=1.0.0
Provides-Extra: dev
Requires-Dist: pytest>=7.0.0; extra == "dev"
Requires-Dist: pytest-cov>=4.0.0; extra == "dev"
Provides-Extra: windows
Requires-Dist: pywin32>=306; extra == "windows"
Requires-Dist: psutil>=5.9.0; extra == "windows"
